tueplots/__init__.py
tueplots/_version.py
tueplots/axes.py
tueplots/bundles.py
tueplots/cycler.py
tueplots/figsizes.py
tueplots/fonts.py
tueplots/fontsizes.py
tueplots/markers.py
tueplots/constants/__init__.py
tueplots/constants/markers.py
tueplots/constants/color/__init__.py
tueplots/constants/color/palettes.py
tueplots/constants/color/rgb.py
tueplots-0.2.3.dist-info/licenses/LICENSE
tueplots-0.2.3.dist-info/METADATA
tueplots-0.2.3.dist-info/WHEEL
tueplots-0.2.3.dist-info/top_level.txt
tueplots-0.2.3.dist-info/RECORD
