Metadata-Version: 2.4
Name: tueplots
Version: 0.2.3
Summary: Scientific plotting made easy.
Author-email: Nicholas Krämer <pekra@dtu.dk>
Classifier: Operating System :: OS Independent
Classifier: Programming Language :: Python
Classifier: Programming Language :: Python :: 3.10
Classifier: Programming Language :: Python :: 3.11
Classifier: Programming Language :: Python :: 3.12
Classifier: Programming Language :: Python :: 3.13
Classifier: Programming Language :: Python :: 3.14
Requires-Python: >=3.10
License-File: LICENSE
Requires-Dist: matplotlib
Requires-Dist: numpy
Provides-Extra: ci
Requires-Dist: tox; extra == "ci"
Provides-Extra: examples
Requires-Dist: jupyter; extra == "examples"
Dynamic: license-file
